azure/cognitiveservices/formrecognizer/__init__.py
azure/cognitiveservices/formrecognizer/form_recognizer_client.py
azure/cognitiveservices/formrecognizer/version.py
azure/cognitiveservices/formrecognizer/models/__init__.py
azure/cognitiveservices/formrecognizer/models/analyze_result.py
azure/cognitiveservices/formrecognizer/models/analyze_result_py3.py
azure/cognitiveservices/formrecognizer/models/error_information.py
azure/cognitiveservices/formrecognizer/models/error_information_py3.py
azure/cognitiveservices/formrecognizer/models/error_response.py
azure/cognitiveservices/formrecognizer/models/error_response_py3.py
azure/cognitiveservices/formrecognizer/models/extracted_key_value_pair.py
azure/cognitiveservices/formrecognizer/models/extracted_key_value_pair_py3.py
azure/cognitiveservices/formrecognizer/models/extracted_page.py
azure/cognitiveservices/formrecognizer/models/extracted_page_py3.py
azure/cognitiveservices/formrecognizer/models/extracted_table.py
azure/cognitiveservices/formrecognizer/models/extracted_table_column.py
azure/cognitiveservices/formrecognizer/models/extracted_table_column_py3.py
azure/cognitiveservices/formrecognizer/models/extracted_table_py3.py
azure/cognitiveservices/formrecognizer/models/extracted_token.py
azure/cognitiveservices/formrecognizer/models/extracted_token_py3.py
azure/cognitiveservices/formrecognizer/models/form_document_report.py
azure/cognitiveservices/formrecognizer/models/form_document_report_py3.py
azure/cognitiveservices/formrecognizer/models/form_operation_error.py
azure/cognitiveservices/formrecognizer/models/form_operation_error_py3.py
azure/cognitiveservices/formrecognizer/models/inner_error.py
azure/cognitiveservices/formrecognizer/models/inner_error_py3.py
azure/cognitiveservices/formrecognizer/models/keys_result.py
azure/cognitiveservices/formrecognizer/models/keys_result_py3.py
azure/cognitiveservices/formrecognizer/models/model_result.py
azure/cognitiveservices/formrecognizer/models/model_result_py3.py
azure_cognitiveservices_formrecognizer-0.1.1.dist-info/METADATA
azure_cognitiveservices_formrecognizer-0.1.1.dist-info/WHEEL
azure_cognitiveservices_formrecognizer-0.1.1.dist-info/top_level.txt
azure_cognitiveservices_formrecognizer-0.1.1.dist-info/RECORD
